arcospx/__init__.py
arcospx/_widget.py
arcospx/cellular_automaton.py
arcospx/napari.yaml
arcospx/utils.py
arcospx/_tests/__init__.py
arcospx/_tests/test_widget.py
arcospx/_tests/test_data/1_growing.tif
arcospx/_tests/test_data/1_growing_track_events_true.tif
arcospx/_tests/test_data/1_growing_true.tif
arcospx/_tests/test_data/4_colliding.tif
arcospx_napari-0.1.4.dist-info/licenses/LICENSE
arcospx_napari-0.1.4.dist-info/METADATA
arcospx_napari-0.1.4.dist-info/WHEEL
arcospx_napari-0.1.4.dist-info/entry_points.txt
arcospx_napari-0.1.4.dist-info/top_level.txt
arcospx_napari-0.1.4.dist-info/RECORD
