Metadata-Version: 2.4
Name: arcosPx-napari
Version: 0.1.4
Summary: A plugin to track spatio-temporal correlations in images
Home-page: https://github.com/pertzlab/arcosPx-napari
Author: Benjamin Grädel
Author-email: benjamin.graedel@unibe.ch
License: BSD-3-Clause
Project-URL: Bug Tracker, https://github.com/pertzlab/arcosPx-napari/issues
Project-URL: Documentation, https://github.com/pertzlab/arcosPx-napari#README.md
Project-URL: Source Code, https://github.com/pertzlab/arcosPx-napari
Project-URL: User Support, https://github.com/pertzlab/arcosPx-napari/issues
Classifier: Development Status :: 2 - Pre-Alpha
Classifier: Framework :: napari
Classifier: Intended Audience :: Developers
Classifier: Operating System :: OS Independent
Classifier: Programming Language :: Python
Classifier: Programming Language :: Python :: 3
Classifier: Programming Language :: Python :: 3 :: Only
Classifier: Programming Language :: Python :: 3.10
Classifier: Programming Language :: Python :: 3.11
Classifier: Programming Language :: Python :: 3.12
Classifier: Programming Language :: Python :: 3.13
Classifier: Topic :: Scientific/Engineering :: Image Processing
Requires-Python: >=3.10
License-File: LICENSE
Requires-Dist: numpy
Requires-Dist: magicgui
Requires-Dist: qtpy
Requires-Dist: arcos4py>=0.3.0
Provides-Extra: testing
Requires-Dist: tox; extra == "testing"
Requires-Dist: pytest; extra == "testing"
Requires-Dist: pytest-cov; extra == "testing"
Requires-Dist: pytest-qt; extra == "testing"
Requires-Dist: napari; extra == "testing"
Requires-Dist: pyqt5; extra == "testing"
Dynamic: license-file
